droombot/__init__.py
droombot/api.py
droombot/bot.py
droombot/cli.py
droombot/config.py
droombot/log.py
droombot/models.py
droombot/py.typed
droombot/utils.py
droombot/version.py
droombot/worker.py
droombot-0.2.0.dist-info/LICENSE
droombot-0.2.0.dist-info/METADATA
droombot-0.2.0.dist-info/WHEEL
droombot-0.2.0.dist-info/entry_points.txt
droombot-0.2.0.dist-info/RECORD
