Metadata-Version: 2.1
Name: droombot
Version: 0.2.0
Summary: A Discord Bot for generating images from text prompts
Home-page: https://github.com/sndrtj/droombot
License: Apache-2.0
Author: Sander Bollen
Author-email: sander@sndrtj.eu
Requires-Python: >=3.10,<4.0
Classifier: Development Status :: 3 - Alpha
Classifier: License :: OSI Approved :: Apache Software License
Classifier: Programming Language :: Python :: 3
Classifier: Programming Language :: Python :: 3.10
Classifier: Programming Language :: Python :: 3.11
Classifier: Programming Language :: Python :: 3.12
Classifier: Topic :: Communications :: Chat
Requires-Dist: aiohttp[speedups] (>=3.8.4,<4.0.0)
Requires-Dist: aiolimiter (>=1.0.0,<2.0.0)
Requires-Dist: click (>=8.1.3,<9.0.0)
Requires-Dist: py-cord[speed] (>=2.4.1,<3.0.0)
Requires-Dist: pydantic (>=2.7.2,<3.0.0)
Requires-Dist: redis[hiredis] (>=4.5.4,<5.0.0)
Requires-Dist: typing-extensions (>=4.12.0,<5.0.0)
